gici_settings
